Module/QuantumOscillators.py
Module/__init__.py
quantumoscillators-0.1.1.dist-info/METADATA
quantumoscillators-0.1.1.dist-info/WHEEL
quantumoscillators-0.1.1.dist-info/top_level.txt
quantumoscillators-0.1.1.dist-info/RECORD
