Metadata-Version: 2.4
Name: QuantumOscillators
Version: 0.1.1
Summary: A package that deals with Quantum Finance, Provides plotting visuals
Author: SaduPostMagazine
Author-email: sadupostrivista@gmail.com
Dynamic: author
Dynamic: author-email
Dynamic: summary
